<annotation>
    <folder>input_images</folder>
    <filename>IMG_3505.jpg</filename>
    <source>
        <database>Unknown</database>
    </source>
    <size>
        <width>1242</width>
        <height>2208</height>
        <depth>3</depth>
    </size>
    <segmented>0</segmented>
    <object>
        <name>Text</name>
        <pose>Unspecified</pose>
        <truncated>0</truncated>
        <occluded>0</occluded>
        <difficult>0</difficult>
        <bndbox>
            <xmin>451</xmin>
            <ymin>105</ymin>
            <xmax>791</xmax>
            <ymax>155</ymax>
        </bndbox>
    </object>
    <object>
        <name>Text</name>
        <pose>Unspecified</pose>
        <truncated>0</truncated>
        <occluded>0</occluded>
        <difficult>0</difficult>
        <bndbox>
            <xmin>79</xmin>
            <ymin>683</ymin>
            <xmax>1161</xmax>
            <ymax>825</ymax>
        </bndbox>
    </object>
    <object>
        <name>Text</name>
        <pose>Unspecified</pose>
        <truncated>0</truncated>
        <occluded>0</occluded>
        <difficult>0</difficult>
        <bndbox>
            <xmin>39</xmin>
            <ymin>1004</ymin>
            <xmax>844</xmax>
            <ymax>1054</ymax>
        </bndbox>
    </object>
    <object>
        <name>Text</name>
        <pose>Unspecified</pose>
        <truncated>0</truncated>
        <occluded>0</occluded>
        <difficult>0</difficult>
        <bndbox>
            <xmin>38</xmin>
            <ymin>1671</ymin>
            <xmax>368</xmax>
            <ymax>1774</ymax>
        </bndbox>
    </object>
    <object>
        <name>Text</name>
        <pose>Unspecified</pose>
        <truncated>0</truncated>
        <occluded>0</occluded>
        <difficult>0</difficult>
        <bndbox>
            <xmin>642</xmin>
            <ymin>1673</ymin>
            <xmax>950</xmax>
            <ymax>1766</ymax>
        </bndbox>
    </object>
    <object>
        <name>Text</name>
        <pose>Unspecified</pose>
        <truncated>0</truncated>
        <occluded>0</occluded>
        <difficult>0</difficult>
        <bndbox>
            <xmin>51</xmin>
            <ymin>2174</ymin>
            <xmax>200</xmax>
            <ymax>2197</ymax>
        </bndbox>
    </object>
    <object>
        <name>Text</name>
        <pose>Unspecified</pose>
        <truncated>0</truncated>
        <occluded>0</occluded>
        <difficult>0</difficult>
        <bndbox>
            <xmin>318</xmin>
            <ymin>2174</ymin>
            <xmax>429</xmax>
            <ymax>2197</ymax>
        </bndbox>
    </object>
    <object>
        <name>Text</name>
        <pose>Unspecified</pose>
        <truncated>0</truncated>
        <occluded>0</occluded>
        <difficult>0</difficult>
        <bndbox>
            <xmin>564</xmin>
            <ymin>2174</ymin>
            <xmax>677</xmax>
            <ymax>2197</ymax>
        </bndbox>
    </object>
    <object>
        <name>Text</name>
        <pose>Unspecified</pose>
        <truncated>0</truncated>
        <occluded>0</occluded>
        <difficult>0</difficult>
        <bndbox>
            <xmin>811</xmin>
            <ymin>2175</ymin>
            <xmax>925</xmax>
            <ymax>2197</ymax>
        </bndbox>
    </object>
    <object>
        <name>Text</name>
        <pose>Unspecified</pose>
        <truncated>0</truncated>
        <occluded>0</occluded>
        <difficult>0</difficult>
        <bndbox>
            <xmin>1030</xmin>
            <ymin>2175</ymin>
            <xmax>1205</xmax>
            <ymax>2197</ymax>
        </bndbox>
    </object>
    <object>
        <name>Icon</name>
        <pose>Unspecified</pose>
        <truncated>0</truncated>
        <occluded>0</occluded>
        <difficult>0</difficult>
        <bndbox>
            <xmin>1076</xmin>
            <ymin>2081</ymin>
            <xmax>1156</xmax>
            <ymax>2155</ymax>
        </bndbox>
    </object>
    <object>
        <name>Icon</name>
        <pose>Unspecified</pose>
        <truncated>0</truncated>
        <occluded>0</occluded>
        <difficult>0</difficult>
        <bndbox>
            <xmin>839</xmin>
            <ymin>2079</ymin>
            <xmax>895</xmax>
            <ymax>2157</ymax>
        </bndbox>
    </object>
    <object>
        <name>Icon</name>
        <pose>Unspecified</pose>
        <truncated>0</truncated>
        <occluded>0</occluded>
        <difficult>0</difficult>
        <bndbox>
            <xmin>581</xmin>
            <ymin>2085</ymin>
            <xmax>658</xmax>
            <ymax>2150</ymax>
        </bndbox>
    </object>
    <object>
        <name>Image</name>
        <pose>Unspecified</pose>
        <truncated>0</truncated>
        <occluded>0</occluded>
        <difficult>0</difficult>
        <bndbox>
            <xmin>331</xmin>
            <ymin>2075</ymin>
            <xmax>415</xmax>
            <ymax>2164</ymax>
        </bndbox>
    </object>
    <object>
        <name>Icon</name>
        <pose>Unspecified</pose>
        <truncated>0</truncated>
        <occluded>0</occluded>
        <difficult>0</difficult>
        <bndbox>
            <xmin>79</xmin>
            <ymin>2075</ymin>
            <xmax>168</xmax>
            <ymax>2164</ymax>
        </bndbox>
    </object>
    <object>
        <name>Image</name>
        <pose>Unspecified</pose>
        <truncated>0</truncated>
        <occluded>0</occluded>
        <difficult>0</difficult>
        <bndbox>
            <xmin>36</xmin>
            <ymin>1849</ymin>
            <xmax>604</xmax>
            <ymax>2060</ymax>
        </bndbox>
    </object>
    <object>
        <name>Image</name>
        <pose>Unspecified</pose>
        <truncated>0</truncated>
        <occluded>0</occluded>
        <difficult>0</difficult>
        <bndbox>
            <xmin>639</xmin>
            <ymin>1849</ymin>
            <xmax>1207</xmax>
            <ymax>2060</ymax>
        </bndbox>
    </object>
    <object>
        <name>Image</name>
        <pose>Unspecified</pose>
        <truncated>0</truncated>
        <occluded>0</occluded>
        <difficult>0</difficult>
        <bndbox>
            <xmin>639</xmin>
            <ymin>1076</ymin>
            <xmax>1207</xmax>
            <ymax>1644</ymax>
        </bndbox>
    </object>
    <object>
        <name>Image</name>
        <pose>Unspecified</pose>
        <truncated>0</truncated>
        <occluded>0</occluded>
        <difficult>0</difficult>
        <bndbox>
            <xmin>36</xmin>
            <ymin>1076</ymin>
            <xmax>604</xmax>
            <ymax>1644</ymax>
        </bndbox>
    </object>
    <object>
        <name>Image</name>
        <pose>Unspecified</pose>
        <truncated>0</truncated>
        <occluded>0</occluded>
        <difficult>0</difficult>
        <bndbox>
            <xmin>455</xmin>
            <ymin>288</ymin>
            <xmax>787</xmax>
            <ymax>617</ymax>
        </bndbox>
    </object>
    <object>
        <name>UpperTaskBar</name>
        <pose>Unspecified</pose>
        <truncated>0</truncated>
        <occluded>0</occluded>
        <difficult>0</difficult>
        <bndbox>
            <xmin>1</xmin>
            <ymin>1</ymin>
            <xmax>1242</xmax>
            <ymax>49</ymax>
        </bndbox>
    </object>
</annotation>
