<annotation>
    <folder>input_images</folder>
    <filename>IMG_8755.jpg</filename>
    <size>
        <width>1242</width>
        <height>2688</height>
        <depth>3</depth>
    </size>
    <object>
        <name>Image</name>
        <difficult>0</difficult>
        <bndbox>
            <xmin>1.000000</xmin>
            <ymin>2328.039795</ymin>
            <xmax>1242.000000</xmax>
            <ymax>2586.259766</ymax>
        </bndbox>
    </object>
    <object>
        <name>Icon</name>
        <difficult>0</difficult>
        <bndbox>
            <xmin>1133.874756</xmin>
            <ymin>2159.058105</ymin>
            <xmax>1169.408447</xmax>
            <ymax>2225.581299</ymax>
        </bndbox>
    </object>
    <object>
        <name>Text</name>
        <difficult>0</difficult>
        <bndbox>
            <xmin>236.549393</xmin>
            <ymin>2184.895752</ymin>
            <xmax>1005.620300</xmax>
            <ymax>2238.645752</ymax>
        </bndbox>
    </object>
    <object>
        <name>Text</name>
        <difficult>0</difficult>
        <bndbox>
            <xmin>394.415741</xmin>
            <ymin>2108.733887</ymin>
            <xmax>850.591614</xmax>
            <ymax>2173.791016</ymax>
        </bndbox>
    </object>
    <object>
        <name>Image</name>
        <difficult>0</difficult>
        <bndbox>
            <xmin>1.053201</xmin>
            <ymin>1641.221069</ymin>
            <xmax>1242.000000</xmax>
            <ymax>2066.347412</ymax>
        </bndbox>
    </object>
    <object>
        <name>Icon</name>
        <difficult>0</difficult>
        <bndbox>
            <xmin>1134.000000</xmin>
            <ymin>1457.000000</ymin>
            <xmax>1169.000000</xmax>
            <ymax>1521.000000</ymax>
        </bndbox>
    </object>
    <object>
        <name>Text</name>
        <difficult>0</difficult>
        <bndbox>
            <xmin>296.491638</xmin>
            <ymin>1498.064575</ymin>
            <xmax>949.580200</xmax>
            <ymax>1551.105957</ymax>
        </bndbox>
    </object>
    <object>
        <name>Text</name>
        <difficult>0</difficult>
        <bndbox>
            <xmin>342.518799</xmin>
            <ymin>1422.138672</ymin>
            <xmax>903.757507</xmax>
            <ymax>1486.956055</ymax>
        </bndbox>
    </object>
    <object>
        <name>Image</name>
        <difficult>0</difficult>
        <bndbox>
            <xmin>1.000000</xmin>
            <ymin>954.506470</ymin>
            <xmax>1242.000000</xmax>
            <ymax>1379.707642</ymax>
        </bndbox>
    </object>
    <object>
        <name>Icon</name>
        <difficult>0</difficult>
        <bndbox>
            <xmin>1135.000000</xmin>
            <ymin>786.000000</ymin>
            <xmax>1169.000000</xmax>
            <ymax>851.000000</ymax>
        </bndbox>
    </object>
    <object>
        <name>Text</name>
        <difficult>0</difficult>
        <bndbox>
            <xmin>381.570160</xmin>
            <ymin>811.534241</ymin>
            <xmax>858.489319</xmax>
            <ymax>853.925842</ymax>
        </bndbox>
    </object>
    <object>
        <name>Text</name>
        <difficult>0</difficult>
        <bndbox>
            <xmin>402.394104</xmin>
            <ymin>735.248596</ymin>
            <xmax>841.596497</xmax>
            <ymax>800.065796</ymax>
        </bndbox>
    </object>
    <object>
        <name>Image</name>
        <difficult>0</difficult>
        <bndbox>
            <xmin>1.000000</xmin>
            <ymin>267.682343</ymin>
            <xmax>1242.000000</xmax>
            <ymax>692.797607</ymax>
        </bndbox>
    </object>
    <object>
        <name>Icon</name>
        <difficult>0</difficult>
        <bndbox>
            <xmin>1115.986328</xmin>
            <ymin>164.848480</ymin>
            <xmax>1182.302124</xmax>
            <ymax>231.111191</ymax>
        </bndbox>
    </object>
    <object>
        <name>Image</name>
        <difficult>0</difficult>
        <bndbox>
            <xmin>369.000000</xmin>
            <ymin>153.000000</ymin>
            <xmax>873.457275</xmax>
            <ymax>244.160858</ymax>
        </bndbox>
    </object>
    <object>
        <name>Icon</name>
        <difficult>0</difficult>
        <bndbox>
            <xmin>60.612301</xmin>
            <ymin>172.865692</ymin>
            <xmax>130.398743</xmax>
            <ymax>223.079346</ymax>
        </bndbox>
    </object>
    <object>
        <name>UpperTaskBar</name>
        <difficult>0</difficult>
        <bndbox>
            <xmin>96.854706</xmin>
            <ymin>49.735382</ymin>
            <xmax>1177.400146</xmax>
            <ymax>87.028809</ymax>
        </bndbox>
    </object>
</annotation>
