<annotation>
    <folder>JPEGImages_Icon</folder>
    <filename>IMG_3871.jpg</filename>
    <size>
        <width>1242</width>
        <height>2208</height>
        <depth>3</depth>
    </size>
    <object>
        <name>TextButton</name>
        <difficult>0</difficult>
        <bndbox>
            <xmin>37</xmin>
            <ymin>1995</ymin>
            <xmax>1205</xmax>
            <ymax>2149</ymax>
        </bndbox>
    </object>
    <object>
        <name>Icon</name>
        <difficult>0</difficult>
        <bndbox>
            <xmin>454</xmin>
            <ymin>449</ymin>
            <xmax>785</xmax>
            <ymax>781</ymax>
        </bndbox>
    </object>
    <object>
        <name>Text</name>
        <difficult>0</difficult>
        <bndbox>
            <xmin>65</xmin>
            <ymin>1196</ymin>
            <xmax>1179</xmax>
            <ymax>1329</ymax>
        </bndbox>
    </object>
    <object>
        <name>Text</name>
        <difficult>0</difficult>
        <bndbox>
            <xmin>169</xmin>
            <ymin>1028</ymin>
            <xmax>1068</xmax>
            <ymax>1091</ymax>
        </bndbox>
    </object>
    <object>
        <name>UpperTaskBar</name>
        <difficult>0</difficult>
        <bndbox>
            <xmin>21</xmin>
            <ymin>15</ymin>
            <xmax>1228</xmax>
            <ymax>46</ymax>
        </bndbox>
    </object>
    <object>
        <name>Icon</name>
        <difficult>0</difficult>
        <bndbox>
            <xmin>66</xmin>
            <ymin>112</ymin>
            <xmax>132</xmax>
            <ymax>172</ymax>
        </bndbox>
    </object>
</annotation>
