<annotation>
    <folder>input_images</folder>
    <filename>IMG_9078.jpg</filename>
    <size>
        <width>1242</width>
        <height>2688</height>
        <depth>3</depth>
    </size>
    <object>
        <name>UpperTaskBar</name>
        <difficult>0</difficult>
        <bndbox>
            <xmin>98.478065</xmin>
            <ymin>50.000000</ymin>
            <xmax>1177.000000</xmax>
            <ymax>87.352905</ymax>
        </bndbox>
    </object>
    <object>
        <name>Text</name>
        <difficult>0</difficult>
        <bndbox>
            <xmin>352.000000</xmin>
            <ymin>2448.000000</ymin>
            <xmax>890.399170</xmax>
            <ymax>2491.000000</ymax>
        </bndbox>
    </object>
    <object>
        <name>TextButton</name>
        <difficult>0</difficult>
        <bndbox>
            <xmin>75.749687</xmin>
            <ymin>2285.933350</ymin>
            <xmax>1167.506836</xmax>
            <ymax>2391.416992</ymax>
        </bndbox>
    </object>
    <object>
        <name>Text</name>
        <difficult>0</difficult>
        <bndbox>
            <xmin>502.332153</xmin>
            <ymin>1606.333008</ymin>
            <xmax>736.690063</xmax>
            <ymax>1667.280151</ymax>
        </bndbox>
    </object>
    <object>
        <name>Text</name>
        <difficult>0</difficult>
        <bndbox>
            <xmin>362.377502</xmin>
            <ymin>1496.089111</ymin>
            <xmax>882.620300</xmax>
            <ymax>1557.515869</ymax>
        </bndbox>
    </object>
    <object>
        <name>Text</name>
        <difficult>0</difficult>
        <bndbox>
            <xmin>496.326996</xmin>
            <ymin>1385.000000</ymin>
            <xmax>747.720398</xmax>
            <ymax>1445.628540</ymax>
        </bndbox>
    </object>
    <object>
        <name>Text</name>
        <difficult>0</difficult>
        <bndbox>
            <xmin>295.000000</xmin>
            <ymin>1050.000000</ymin>
            <xmax>946.000000</xmax>
            <ymax>1308.000000</ymax>
        </bndbox>
    </object>
    <object>
        <name>Image</name>
        <difficult>0</difficult>
        <bndbox>
            <xmin>537.000000</xmin>
            <ymin>239.000000</ymin>
            <xmax>708.000000</xmax>
            <ymax>305.000000</ymax>
        </bndbox>
    </object>
</annotation>
