<annotation>
    <folder>input_images_Temp</folder>
    <filename>IMG_1340.jpg</filename>
    <source>
        <database>Unknown</database>
    </source>
    <size>
        <width>1242</width>
        <height>2208</height>
        <depth>3</depth>
    </size>
    <segmented>0</segmented>
    <object>
        <name>UpperTaskBar</name>
        <pose>Unspecified</pose>
        <truncated>0</truncated>
        <occluded>0</occluded>
        <difficult>0</difficult>
        <bndbox>
            <xmin>1</xmin>
            <ymin>1</ymin>
            <xmax>1242</xmax>
            <ymax>49</ymax>
        </bndbox>
    </object>
    <object>
        <name>Text</name>
        <pose>Unspecified</pose>
        <truncated>0</truncated>
        <occluded>0</occluded>
        <difficult>0</difficult>
        <bndbox>
            <xmin>53</xmin>
            <ymin>224</ymin>
            <xmax>399</xmax>
            <ymax>289</ymax>
        </bndbox>
    </object>
    <object>
        <name>Text</name>
        <pose>Unspecified</pose>
        <truncated>0</truncated>
        <occluded>0</occluded>
        <difficult>0</difficult>
        <bndbox>
            <xmin>47</xmin>
            <ymin>721</ymin>
            <xmax>691</xmax>
            <ymax>773</ymax>
        </bndbox>
    </object>
    <object>
        <name>Text</name>
        <pose>Unspecified</pose>
        <truncated>0</truncated>
        <occluded>0</occluded>
        <difficult>0</difficult>
        <bndbox>
            <xmin>49</xmin>
            <ymin>865</ymin>
            <xmax>853</xmax>
            <ymax>904</ymax>
        </bndbox>
    </object>
    <object>
        <name>Text</name>
        <pose>Unspecified</pose>
        <truncated>0</truncated>
        <occluded>0</occluded>
        <difficult>0</difficult>
        <bndbox>
            <xmin>50</xmin>
            <ymin>1394</ymin>
            <xmax>792</xmax>
            <ymax>1456</ymax>
        </bndbox>
    </object>
    <object>
        <name>Text</name>
        <pose>Unspecified</pose>
        <truncated>0</truncated>
        <occluded>0</occluded>
        <difficult>0</difficult>
        <bndbox>
            <xmin>49</xmin>
            <ymin>1537</ymin>
            <xmax>848</xmax>
            <ymax>1577</ymax>
        </bndbox>
    </object>
    <object>
        <name>Text</name>
        <pose>Unspecified</pose>
        <truncated>0</truncated>
        <occluded>0</occluded>
        <difficult>0</difficult>
        <bndbox>
            <xmin>148</xmin>
            <ymin>2173</ymin>
            <xmax>269</xmax>
            <ymax>2197</ymax>
        </bndbox>
    </object>
    <object>
        <name>Text</name>
        <pose>Unspecified</pose>
        <truncated>0</truncated>
        <occluded>0</occluded>
        <difficult>0</difficult>
        <bndbox>
            <xmin>580</xmin>
            <ymin>2172</ymin>
            <xmax>663</xmax>
            <ymax>2203</ymax>
        </bndbox>
    </object>
    <object>
        <name>Text</name>
        <pose>Unspecified</pose>
        <truncated>0</truncated>
        <occluded>0</occluded>
        <difficult>0</difficult>
        <bndbox>
            <xmin>954</xmin>
            <ymin>2171</ymin>
            <xmax>1113</xmax>
            <ymax>2203</ymax>
        </bndbox>
    </object>
    <object>
        <name>Icon</name>
        <pose>Unspecified</pose>
        <truncated>0</truncated>
        <occluded>0</occluded>
        <difficult>0</difficult>
        <bndbox>
            <xmin>170</xmin>
            <ymin>2081</ymin>
            <xmax>244</xmax>
            <ymax>2155</ymax>
        </bndbox>
    </object>
    <object>
        <name>Image</name>
        <pose>Unspecified</pose>
        <truncated>0</truncated>
        <occluded>0</occluded>
        <difficult>0</difficult>
        <bndbox>
            <xmin>583</xmin>
            <ymin>2080</ymin>
            <xmax>658</xmax>
            <ymax>2154</ymax>
        </bndbox>
    </object>
    <object>
        <name>Image</name>
        <pose>Unspecified</pose>
        <truncated>0</truncated>
        <occluded>0</occluded>
        <difficult>0</difficult>
        <bndbox>
            <xmin>988</xmin>
            <ymin>2075</ymin>
            <xmax>1080</xmax>
            <ymax>2157</ymax>
        </bndbox>
    </object>
    <object>
        <name>Image</name>
        <pose>Unspecified</pose>
        <truncated>0</truncated>
        <occluded>0</occluded>
        <difficult>0</difficult>
        <bndbox>
            <xmin>1</xmin>
            <ymin>331</ymin>
            <xmax>1242</xmax>
            <ymax>826</ymax>
        </bndbox>
    </object>
    <object>
        <name>Image</name>
        <pose>Unspecified</pose>
        <truncated>0</truncated>
        <occluded>0</occluded>
        <difficult>0</difficult>
        <bndbox>
            <xmin>1</xmin>
            <ymin>1004</ymin>
            <xmax>1242</xmax>
            <ymax>1499</ymax>
        </bndbox>
    </object>
    <object>
        <name>Image</name>
        <pose>Unspecified</pose>
        <truncated>0</truncated>
        <occluded>0</occluded>
        <difficult>0</difficult>
        <bndbox>
            <xmin>1</xmin>
            <ymin>1675</ymin>
            <xmax>1242</xmax>
            <ymax>2061</ymax>
        </bndbox>
    </object>
</annotation>
