<annotation>
    <folder>input_images</folder>
    <filename>IMG_3852.jpg</filename>
    <size>
        <width>1242</width>
        <height>2208</height>
        <depth>3</depth>
    </size>
    <segmented>0</segmented>
    <object>
        <name>Icon</name>
        <pose>Unspecified</pose>
        <truncated>0</truncated>
        <occluded>0</occluded>
        <difficult>0</difficult>
        <bndbox>
            <xmin>101</xmin>
            <ymin>77</ymin>
            <xmax>168</xmax>
            <ymax>127</ymax>
        </bndbox>
    </object>
    <object>
        <name>Text</name>
        <pose>Unspecified</pose>
        <truncated>0</truncated>
        <occluded>0</occluded>
        <difficult>0</difficult>
        <bndbox>
            <xmin>93</xmin>
            <ymin>142</ymin>
            <xmax>175</xmax>
            <ymax>174</ymax>
        </bndbox>
    </object>
    <object>
        <name>UpperTaskBar</name>
        <pose>Unspecified</pose>
        <truncated>0</truncated>
        <occluded>0</occluded>
        <difficult>0</difficult>
        <bndbox>
            <xmin>19</xmin>
            <ymin>14</ymin>
            <xmax>1228</xmax>
            <ymax>47</ymax>
        </bndbox>
    </object>
    <object>
        <name>Text</name>
        <pose>Unspecified</pose>
        <truncated>0</truncated>
        <occluded>0</occluded>
        <difficult>0</difficult>
        <bndbox>
            <xmin>486</xmin>
            <ymin>95</ymin>
            <xmax>758</xmax>
            <ymax>146</ymax>
        </bndbox>
    </object>
    <object>
        <name>TextButton</name>
        <pose>Unspecified</pose>
        <truncated>0</truncated>
        <occluded>0</occluded>
        <difficult>0</difficult>
        <bndbox>
            <xmin>246</xmin>
            <ymin>1356</ymin>
            <xmax>997</xmax>
            <ymax>1493</ymax>
        </bndbox>
    </object>
    <object>
        <name>Text</name>
        <pose>Unspecified</pose>
        <truncated>0</truncated>
        <occluded>0</occluded>
        <difficult>0</difficult>
        <bndbox>
            <xmin>298</xmin>
            <ymin>1181</ymin>
            <xmax>947</xmax>
            <ymax>1294</ymax>
        </bndbox>
    </object>
    <object>
        <name>Text</name>
        <pose>Unspecified</pose>
        <truncated>0</truncated>
        <occluded>0</occluded>
        <difficult>0</difficult>
        <bndbox>
            <xmin>272</xmin>
            <ymin>1053</ymin>
            <xmax>972</xmax>
            <ymax>1102</ymax>
        </bndbox>
    </object>
    <object>
        <name>Icon</name>
        <pose>Unspecified</pose>
        <truncated>0</truncated>
        <occluded>0</occluded>
        <difficult>0</difficult>
        <bndbox>
            <xmin>586</xmin>
            <ymin>908</ymin>
            <xmax>656</xmax>
            <ymax>988</ymax>
        </bndbox>
    </object>
</annotation>
