<annotation>
    <folder>input_images</folder>
    <filename>Android_598.jpg</filename>
    <size>
        <width>720</width>
        <height>1280</height>
        <depth>3</depth>
    </size>
    <segmented>0</segmented>
    <object>
        <name>Text</name>
        <pose>Unspecified</pose>
        <truncated>0</truncated>
        <occluded>0</occluded>
        <difficult>0</difficult>
        <bndbox>
            <xmin>203</xmin>
            <ymin>1108</ymin>
            <xmax>547</xmax>
            <ymax>1170</ymax>
        </bndbox>
    </object>
    <object>
        <name>Image</name>
        <pose>Unspecified</pose>
        <truncated>0</truncated>
        <occluded>0</occluded>
        <difficult>0</difficult>
        <bndbox>
            <xmin>63</xmin>
            <ymin>1083</ymin>
            <xmax>176</xmax>
            <ymax>1195</ymax>
        </bndbox>
    </object>
    <object>
        <name>Text</name>
        <pose>Unspecified</pose>
        <truncated>0</truncated>
        <occluded>0</occluded>
        <difficult>0</difficult>
        <bndbox>
            <xmin>206</xmin>
            <ymin>932</ymin>
            <xmax>515</xmax>
            <ymax>956</ymax>
        </bndbox>
    </object>
    <object>
        <name>Image</name>
        <pose>Unspecified</pose>
        <truncated>0</truncated>
        <occluded>0</occluded>
        <difficult>0</difficult>
        <bndbox>
            <xmin>63</xmin>
            <ymin>888</ymin>
            <xmax>176</xmax>
            <ymax>1001</ymax>
        </bndbox>
    </object>
    <object>
        <name>TextButton</name>
        <pose>Unspecified</pose>
        <truncated>0</truncated>
        <occluded>0</occluded>
        <difficult>0</difficult>
        <bndbox>
            <xmin>35</xmin>
            <ymin>1056</ymin>
            <xmax>685</xmax>
            <ymax>1225</ymax>
        </bndbox>
    </object>
    <object>
        <name>TextButton</name>
        <pose>Unspecified</pose>
        <truncated>0</truncated>
        <occluded>0</occluded>
        <difficult>0</difficult>
        <bndbox>
            <xmin>35</xmin>
            <ymin>859</ymin>
            <xmax>685</xmax>
            <ymax>1028</ymax>
        </bndbox>
    </object>
    <object>
        <name>Text</name>
        <pose>Unspecified</pose>
        <truncated>0</truncated>
        <occluded>0</occluded>
        <difficult>0</difficult>
        <bndbox>
            <xmin>35</xmin>
            <ymin>311</ymin>
            <xmax>626</xmax>
            <ymax>379</ymax>
        </bndbox>
    </object>
    <object>
        <name>Text</name>
        <pose>Unspecified</pose>
        <truncated>0</truncated>
        <occluded>0</occluded>
        <difficult>0</difficult>
        <bndbox>
            <xmin>39</xmin>
            <ymin>154</ymin>
            <xmax>623</xmax>
            <ymax>275</ymax>
        </bndbox>
    </object>
    <object>
        <name>UpperTaskBar</name>
        <pose>Unspecified</pose>
        <truncated>0</truncated>
        <occluded>0</occluded>
        <difficult>0</difficult>
        <bndbox>
            <xmin>1</xmin>
            <ymin>1</ymin>
            <xmax>720</xmax>
            <ymax>34</ymax>
        </bndbox>
    </object>
</annotation>