<annotation>
    <folder>input_images</folder>
    <filename>28881.jpg</filename>
    <source>
        <database>Unknown</database>
    </source>
    <size>
        <width>1080</width>
        <height>1794</height>
        <depth>3</depth>
    </size>
    <segmented>0</segmented>
    <object>
        <name>TextButton</name>
        <pose>Unspecified</pose>
        <truncated>0</truncated>
        <occluded>0</occluded>
        <difficult>0</difficult>
        <bndbox>
            <xmin>198</xmin>
            <ymin>1258</ymin>
            <xmax>882</xmax>
            <ymax>1410</ymax>
        </bndbox>
    </object>
    <object>
        <name>Text</name>
        <pose>Unspecified</pose>
        <truncated>0</truncated>
        <occluded>0</occluded>
        <difficult>0</difficult>
        <bndbox>
            <xmin>143</xmin>
            <ymin>1135</ymin>
            <xmax>936</xmax>
            <ymax>1226</ymax>
        </bndbox>
    </object>
    <object>
        <name>Image</name>
        <pose>Unspecified</pose>
        <truncated>0</truncated>
        <occluded>0</occluded>
        <difficult>0</difficult>
        <bndbox>
            <xmin>371</xmin>
            <ymin>762</ymin>
            <xmax>715</xmax>
            <ymax>997</ymax>
        </bndbox>
    </object>
    <object>
        <name>Text</name>
        <pose>Unspecified</pose>
        <truncated>0</truncated>
        <occluded>0</occluded>
        <difficult>0</difficult>
        <bndbox>
            <xmin>271</xmin>
            <ymin>518</ymin>
            <xmax>812</xmax>
            <ymax>568</ymax>
        </bndbox>
    </object>
    <object>
        <name>Modal</name>
        <pose>Unspecified</pose>
        <truncated>0</truncated>
        <occluded>0</occluded>
        <difficult>0</difficult>
        <bndbox>
            <xmin>69</xmin>
            <ymin>430</ymin>
            <xmax>1012</xmax>
            <ymax>1428</ymax>
        </bndbox>
    </object>
<object><name>UpperTaskBar</name><pose>Unspecified</pose><truncated>0</truncated><difficult>0</difficult><bndbox><xmin>1</xmin><ymin>1</ymin><xmax>1080</xmax><ymax>64</ymax></bndbox></object></annotation>
