<annotation>
    <folder>input_images</folder>
    <filename>48491.jpg</filename>
    <source>
        <database>Unknown</database>
    </source>
    <size>
        <width>1080</width>
        <height>1794</height>
        <depth>3</depth>
    </size>
    <segmented>0</segmented>
    <object>
        <name>Text</name>
        <pose>Unspecified</pose>
        <truncated>0</truncated>
        <occluded>0</occluded>
        <difficult>0</difficult>
        <bndbox>
            <xmin>89</xmin>
            <ymin>1031</ymin>
            <xmax>290</xmax>
            <ymax>1069</ymax>
        </bndbox>
    </object>
    <object>
        <name>Text</name>
        <pose>Unspecified</pose>
        <truncated>0</truncated>
        <occluded>0</occluded>
        <difficult>0</difficult>
        <bndbox>
            <xmin>87</xmin>
            <ymin>886</ymin>
            <xmax>296</xmax>
            <ymax>921</ymax>
        </bndbox>
    </object>
    <object>
        <name>Image</name>
        <pose>Unspecified</pose>
        <truncated>0</truncated>
        <occluded>0</occluded>
        <difficult>0</difficult>
        <bndbox>
            <xmin>973</xmin>
            <ymin>147</ymin>
            <xmax>1033</xmax>
            <ymax>207</ymax>
        </bndbox>
    </object>
    <object>
        <name>Icon</name>
        <pose>Unspecified</pose>
        <truncated>0</truncated>
        <occluded>0</occluded>
        <difficult>0</difficult>
        <bndbox>
            <xmin>875</xmin>
            <ymin>147</ymin>
            <xmax>919</xmax>
            <ymax>212</ymax>
        </bndbox>
    </object>
    <object>
        <name>Image</name>
        <pose>Unspecified</pose>
        <truncated>0</truncated>
        <occluded>0</occluded>
        <difficult>0</difficult>
        <bndbox>
            <xmin>212</xmin>
            <ymin>401</ymin>
            <xmax>869</xmax>
            <ymax>561</ymax>
        </bndbox>
    </object>
    <object>
        <name>EditText</name>
        <pose>Unspecified</pose>
        <truncated>0</truncated>
        <occluded>0</occluded>
        <difficult>0</difficult>
        <bndbox>
            <xmin>63</xmin>
            <ymin>886</ymin>
            <xmax>1018</xmax>
            <ymax>945</ymax>
        </bndbox>
    </object>
    <object>
        <name>EditText</name>
        <pose>Unspecified</pose>
        <truncated>0</truncated>
        <occluded>0</occluded>
        <difficult>0</difficult>
        <bndbox>
            <xmin>63</xmin>
            <ymin>1031</ymin>
            <xmax>1018</xmax>
            <ymax>1093</ymax>
        </bndbox>
    </object>
    <object>
        <name>Text</name>
        <pose>Unspecified</pose>
        <truncated>0</truncated>
        <occluded>0</occluded>
        <difficult>0</difficult>
        <bndbox>
            <xmin>487</xmin>
            <ymin>1140</ymin>
            <xmax>743</xmax>
            <ymax>1170</ymax>
        </bndbox>
    </object>
    <object>
        <name>Switch</name>
        <pose>Unspecified</pose>
        <truncated>0</truncated>
        <occluded>0</occluded>
        <difficult>0</difficult>
        <bndbox>
            <xmin>762</xmin>
            <ymin>1117</ymin>
            <xmax>1022</xmax>
            <ymax>1192</ymax>
        </bndbox>
    </object>
    <object>
        <name>TextButton</name>
        <pose>Unspecified</pose>
        <truncated>0</truncated>
        <occluded>0</occluded>
        <difficult>0</difficult>
        <bndbox>
            <xmin>53</xmin>
            <ymin>1327</ymin>
            <xmax>1028</xmax>
            <ymax>1455</ymax>
        </bndbox>
    </object>
    <object>
        <name>Text</name>
        <pose>Unspecified</pose>
        <truncated>0</truncated>
        <occluded>0</occluded>
        <difficult>0</difficult>
        <bndbox>
            <xmin>210</xmin>
            <ymin>1600</ymin>
            <xmax>436</xmax>
            <ymax>1638</ymax>
        </bndbox>
    </object>
    <object>
        <name>Text</name>
        <pose>Unspecified</pose>
        <truncated>0</truncated>
        <occluded>0</occluded>
        <difficult>0</difficult>
        <bndbox>
            <xmin>496</xmin>
            <ymin>1602</ymin>
            <xmax>560</xmax>
            <ymax>1634</ymax>
        </bndbox>
    </object>
    <object>
        <name>Text</name>
        <pose>Unspecified</pose>
        <truncated>0</truncated>
        <occluded>0</occluded>
        <difficult>0</difficult>
        <bndbox>
            <xmin>619</xmin>
            <ymin>1600</ymin>
            <xmax>868</xmax>
            <ymax>1638</ymax>
        </bndbox>
    </object>
    <object>
        <name>Text</name>
        <pose>Unspecified</pose>
        <truncated>0</truncated>
        <occluded>0</occluded>
        <difficult>0</difficult>
        <bndbox>
            <xmin>340</xmin>
            <ymin>1662</ymin>
            <xmax>741</xmax>
            <ymax>1684</ymax>
        </bndbox>
    </object>
    <object>
        <name>Text</name>
        <pose>Unspecified</pose>
        <truncated>0</truncated>
        <occluded>0</occluded>
        <difficult>0</difficult>
        <bndbox>
            <xmin>322</xmin>
            <ymin>1713</ymin>
            <xmax>761</xmax>
            <ymax>1740</ymax>
        </bndbox>
    </object>
    <object>
        <name>UpperTaskBar</name>
        <pose>Unspecified</pose>
        <truncated>0</truncated>
        <occluded>0</occluded>
        <difficult>0</difficult>
        <bndbox>
            <xmin>1</xmin>
            <ymin>1</ymin>
            <xmax>1080</xmax>
            <ymax>64</ymax>
        </bndbox>
    </object>
</annotation>
