<annotation>
    <folder>input_images</folder>
    <filename>54204.jpg</filename>
    <size>
        <width>1080</width>
        <height>1794</height>
        <depth>3</depth>
    </size>
    <object>
        <name>UpperTaskBar</name>
        <difficult>0</difficult>
        <bndbox>
            <xmin>1</xmin>
            <ymin>1</ymin>
            <xmax>1080</xmax>
            <ymax>54</ymax>
        </bndbox>
    </object>
    <object>
        <name>Text</name>
        <difficult>0</difficult>
        <bndbox>
            <xmin>207</xmin>
            <ymin>296</ymin>
            <xmax>873</xmax>
            <ymax>456</ymax>
        </bndbox>
    </object>
    <object>
        <name>EditText</name>
        <difficult>0</difficult>
        <bndbox>
            <xmin>186</xmin>
            <ymin>508</ymin>
            <xmax>895</xmax>
            <ymax>638</ymax>
        </bndbox>
    </object>
    <object>
        <name>Text</name>
        <difficult>0</difficult>
        <bndbox>
            <xmin>494</xmin>
            <ymin>555</ymin>
            <xmax>581</xmax>
            <ymax>584</ymax>
        </bndbox>
    </object>
    <object>
        <name>EditText</name>
        <difficult>0</difficult>
        <bndbox>
            <xmin>185</xmin>
            <ymin>663</ymin>
            <xmax>895</xmax>
            <ymax>793</ymax>
        </bndbox>
    </object>
    <object>
        <name>Text</name>
        <difficult>0</difficult>
        <bndbox>
            <xmin>455</xmin>
            <ymin>713</ymin>
            <xmax>610</xmax>
            <ymax>741</ymax>
        </bndbox>
    </object>
    <object>
        <name>EditText</name>
        <difficult>0</difficult>
        <bndbox>
            <xmin>185</xmin>
            <ymin>818</ymin>
            <xmax>895</xmax>
            <ymax>948</ymax>
        </bndbox>
    </object>
    <object>
        <name>Text</name>
        <difficult>0</difficult>
        <bndbox>
            <xmin>463</xmin>
            <ymin>866</ymin>
            <xmax>618</xmax>
            <ymax>894</ymax>
        </bndbox>
    </object>
    <object>
        <name>Text</name>
        <difficult>0</difficult>
        <bndbox>
            <xmin>295</xmin>
            <ymin>984</ymin>
            <xmax>658</xmax>
            <ymax>1059</ymax>
        </bndbox>
    </object>
    <object>
        <name>CheckedTextView</name>
        <difficult>0</difficult>
        <bndbox>
            <xmin>204</xmin>
            <ymin>984</ymin>
            <xmax>658</xmax>
            <ymax>1060</ymax>
        </bndbox>
    </object>
    <object>
        <name>TextButton</name>
        <difficult>0</difficult>
        <bndbox>
            <xmin>185</xmin>
            <ymin>1084</ymin>
            <xmax>895</xmax>
            <ymax>1213</ymax>
        </bndbox>
    </object>
    <object>
        <name>Text</name>
        <difficult>0</difficult>
        <bndbox>
            <xmin>513</xmin>
            <ymin>1258</ymin>
            <xmax>567</xmax>
            <ymax>1290</ymax>
        </bndbox>
    </object>
    <object>
        <name>TextButton</name>
        <difficult>0</difficult>
        <bndbox>
            <xmin>186</xmin>
            <ymin>1333</ymin>
            <xmax>895</xmax>
            <ymax>1461</ymax>
        </bndbox>
    </object>
    <object>
        <name>Text</name>
        <difficult>0</difficult>
        <bndbox>
            <xmin>433</xmin>
            <ymin>1547</ymin>
            <xmax>648</xmax>
            <ymax>1588</ymax>
        </bndbox>
    </object>
    <object>
        <name>BackgroundImage</name>
        <difficult>0</difficult>
        <bndbox>
            <xmin>1</xmin>
            <ymin>54</ymin>
            <xmax>1080</xmax>
            <ymax>1794</ymax>
        </bndbox>
    </object>
</annotation>
