<annotation>
    <folder>input_images_new</folder>
    <filename>55309.jpg</filename>
    <source>
        <database>Unknown</database>
    </source>
    <size>
        <width>540</width>
        <height>897</height>
        <depth>3</depth>
    </size>
    <segmented>0</segmented>
    <object>
        <name>Image</name>
        <pose>Unspecified</pose>
        <truncated>0</truncated>
        <occluded>0</occluded>
        <difficult>0</difficult>
        <bndbox>
            <xmin>94</xmin>
            <ymin>108</ymin>
            <xmax>441</xmax>
            <ymax>478</ymax>
        </bndbox>
    </object>
    <object>
        <name>Text</name>
        <pose>Unspecified</pose>
        <truncated>0</truncated>
        <occluded>0</occluded>
        <difficult>0</difficult>
        <bndbox>
            <xmin>180</xmin>
            <ymin>537</ymin>
            <xmax>360</xmax>
            <ymax>556</ymax>
        </bndbox>
    </object>
    <object>
        <name>Text</name>
        <pose>Unspecified</pose>
        <truncated>0</truncated>
        <occluded>0</occluded>
        <difficult>0</difficult>
        <bndbox>
            <xmin>144</xmin>
            <ymin>575</ymin>
            <xmax>398</xmax>
            <ymax>631</ymax>
        </bndbox>
    </object>
    <object>
        <name>PageIndicator</name>
        <pose>Unspecified</pose>
        <truncated>0</truncated>
        <occluded>0</occluded>
        <difficult>0</difficult>
        <bndbox>
            <xmin>237</xmin>
            <ymin>673</ymin>
            <xmax>294</xmax>
            <ymax>689</ymax>
        </bndbox>
    </object>
    <object>
        <name>TextButton</name>
        <pose>Unspecified</pose>
        <truncated>0</truncated>
        <occluded>0</occluded>
        <difficult>0</difficult>
        <bndbox>
            <xmin>112</xmin>
            <ymin>755</ymin>
            <xmax>429</xmax>
            <ymax>836</ymax>
        </bndbox>
    </object>
</annotation>