<annotation>
    <folder>JPEGImages</folder>
    <filename>61631.jpg</filename>
    <size>
        <width>1080</width>
        <height>1794</height>
        <depth>3</depth>
    </size>
    <object>
        <name>Modal</name>
        <difficult>0</difficult>
        <bndbox>
            <xmin>159</xmin>
            <ymin>455</ymin>
            <xmax>921</xmax>
            <ymax>1340</ymax>
        </bndbox>
    </object>
    <object>
        <name>Text</name>
        <difficult>0</difficult>
        <bndbox>
            <xmin>251</xmin>
            <ymin>557</ymin>
            <xmax>830</xmax>
            <ymax>690</ymax>
        </bndbox>
    </object>
    <object>
        <name>Text</name>
        <difficult>0</difficult>
        <bndbox>
            <xmin>231</xmin>
            <ymin>735</ymin>
            <xmax>848</xmax>
            <ymax>871</ymax>
        </bndbox>
    </object>
    <object>
        <name>Image</name>
        <difficult>0</difficult>
        <bndbox>
            <xmin>225</xmin>
            <ymin>925</ymin>
            <xmax>305</xmax>
            <ymax>1005</ymax>
        </bndbox>
    </object>
    <object>
        <name>CheckedTextView</name>
        <difficult>0</difficult>
        <bndbox>
            <xmin>332</xmin>
            <ymin>936</ymin>
            <xmax>882</xmax>
            <ymax>995</ymax>
        </bndbox>
    </object>
    <object>
        <name>Text</name>
        <difficult>0</difficult>
        <bndbox>
            <xmin>332</xmin>
            <ymin>945</ymin>
            <xmax>525</xmax>
            <ymax>992</ymax>
        </bndbox>
    </object>
    <object>
        <name>Image</name>
        <difficult>0</difficult>
        <bndbox>
            <xmin>225</xmin>
            <ymin>1059</ymin>
            <xmax>306</xmax>
            <ymax>1141</ymax>
        </bndbox>
    </object>
    <object>
        <name>CheckedTextView</name>
        <difficult>0</difficult>
        <bndbox>
            <xmin>333</xmin>
            <ymin>1070</ymin>
            <xmax>882</xmax>
            <ymax>1129</ymax>
        </bndbox>
    </object>
    <object>
        <name>Text</name>
        <difficult>0</difficult>
        <bndbox>
            <xmin>333</xmin>
            <ymin>1079</ymin>
            <xmax>424</xmax>
            <ymax>1117</ymax>
        </bndbox>
    </object>
</annotation>
