<annotation>
    <folder>input_images</folder>
    <filename>69077.jpg</filename>
    <source>
        <database>Unknown</database>
    </source>
    <size>
        <width>1080</width>
        <height>1794</height>
        <depth>3</depth>
    </size>
    <segmented>0</segmented>
    <object>
        <name>Image</name>
        <pose>Unspecified</pose>
        <truncated>0</truncated>
        <occluded>0</occluded>
        <difficult>0</difficult>
        <bndbox>
            <xmin>293</xmin>
            <ymin>455</ymin>
            <xmax>795</xmax>
            <ymax>988</ymax>
        </bndbox>
    </object>
    <object>
        <name>Text</name>
        <pose>Unspecified</pose>
        <truncated>0</truncated>
        <occluded>0</occluded>
        <difficult>0</difficult>
        <bndbox>
            <xmin>79</xmin>
            <ymin>1203</ymin>
            <xmax>1003</xmax>
            <ymax>1340</ymax>
        </bndbox>
    </object>
    <object>
        <name>Text</name>
        <pose>Unspecified</pose>
        <truncated>0</truncated>
        <occluded>0</occluded>
        <difficult>0</difficult>
        <bndbox>
            <xmin>386</xmin>
            <ymin>87</ymin>
            <xmax>829</xmax>
            <ymax>129</ymax>
        </bndbox>
    </object>
    <object>
        <name>Text</name>
        <pose>Unspecified</pose>
        <truncated>0</truncated>
        <occluded>0</occluded>
        <difficult>0</difficult>
        <bndbox>
            <xmin>854</xmin>
            <ymin>88</ymin>
            <xmax>947</xmax>
            <ymax>129</ymax>
        </bndbox>
    </object>
    <object>
        <name>TextButton</name>
        <pose>Unspecified</pose>
        <truncated>0</truncated>
        <occluded>0</occluded>
        <difficult>0</difficult>
        <bndbox>
            <xmin>53</xmin>
            <ymin>1620</ymin>
            <xmax>1028</xmax>
            <ymax>1737</ymax>
        </bndbox>
    </object>
</annotation>