<annotation>
    <folder>input_images</folder>
    <filename>6912.jpg</filename>
    <source>
        <database>Unknown</database>
    </source>
    <size>
        <width>1080</width>
        <height>1794</height>
        <depth>3</depth>
    </size>
    <segmented>0</segmented>
    <object>
        <name>Text</name>
        <pose>Unspecified</pose>
        <truncated>0</truncated>
        <occluded>0</occluded>
        <difficult>0</difficult>
        <bndbox>
            <xmin>839</xmin>
            <ymin>1354</ymin>
            <xmax>1020</xmax>
            <ymax>1394</ymax>
        </bndbox>
    </object>
    <object>
        <name>Text</name>
        <pose>Unspecified</pose>
        <truncated>0</truncated>
        <occluded>0</occluded>
        <difficult>0</difficult>
        <bndbox>
            <xmin>750</xmin>
            <ymin>890</ymin>
            <xmax>953</xmax>
            <ymax>929</ymax>
        </bndbox>
    </object>
    <object>
        <name>Text</name>
        <pose>Unspecified</pose>
        <truncated>0</truncated>
        <occluded>0</occluded>
        <difficult>0</difficult>
        <bndbox>
            <xmin>745</xmin>
            <ymin>775</ymin>
            <xmax>1008</xmax>
            <ymax>807</ymax>
        </bndbox>
    </object>
    <object>
        <name>Text</name>
        <pose>Unspecified</pose>
        <truncated>0</truncated>
        <occluded>0</occluded>
        <difficult>0</difficult>
        <bndbox>
            <xmin>835</xmin>
            <ymin>639</ymin>
            <xmax>979</xmax>
            <ymax>692</ymax>
        </bndbox>
    </object>
    <object>
        <name>Icon</name>
        <pose>Unspecified</pose>
        <truncated>0</truncated>
        <occluded>0</occluded>
        <difficult>0</difficult>
        <bndbox>
            <xmin>992</xmin>
            <ymin>113</ymin>
            <xmax>1040</xmax>
            <ymax>162</ymax>
        </bndbox>
    </object>
    <object>
        <name>Icon</name>
        <pose>Unspecified</pose>
        <truncated>0</truncated>
        <occluded>0</occluded>
        <difficult>0</difficult>
        <bndbox>
            <xmin>52</xmin>
            <ymin>114</ymin>
            <xmax>98</xmax>
            <ymax>161</ymax>
        </bndbox>
    </object>
    <object>
        <name>Icon</name>
        <pose>Unspecified</pose>
        <truncated>0</truncated>
        <occluded>0</occluded>
        <difficult>0</difficult>
        <bndbox>
            <xmin>210</xmin>
            <ymin>198</ymin>
            <xmax>527</xmax>
            <ymax>517</ymax>
        </bndbox>
    </object>
    <object>
        <name>Text</name>
        <pose>Unspecified</pose>
        <truncated>0</truncated>
        <occluded>0</occluded>
        <difficult>0</difficult>
        <bndbox>
            <xmin>191</xmin>
            <ymin>614</ymin>
            <xmax>334</xmax>
            <ymax>651</ymax>
        </bndbox>
    </object>
    <object>
        <name>Text</name>
        <pose>Unspecified</pose>
        <truncated>0</truncated>
        <occluded>0</occluded>
        <difficult>0</difficult>
        <bndbox>
            <xmin>191</xmin>
            <ymin>740</ymin>
            <xmax>295</xmax>
            <ymax>776</ymax>
        </bndbox>
    </object>
    <object>
        <name>Text</name>
        <pose>Unspecified</pose>
        <truncated>0</truncated>
        <occluded>0</occluded>
        <difficult>0</difficult>
        <bndbox>
            <xmin>189</xmin>
            <ymin>866</ymin>
            <xmax>311</xmax>
            <ymax>902</ymax>
        </bndbox>
    </object>
    <object>
        <name>Text</name>
        <pose>Unspecified</pose>
        <truncated>0</truncated>
        <occluded>0</occluded>
        <difficult>0</difficult>
        <bndbox>
            <xmin>191</xmin>
            <ymin>991</ymin>
            <xmax>291</xmax>
            <ymax>1027</ymax>
        </bndbox>
    </object>
    <object>
        <name>Text</name>
        <pose>Unspecified</pose>
        <truncated>0</truncated>
        <occluded>0</occluded>
        <difficult>0</difficult>
        <bndbox>
            <xmin>189</xmin>
            <ymin>1118</ymin>
            <xmax>346</xmax>
            <ymax>1162</ymax>
        </bndbox>
    </object>
    <object>
        <name>Icon</name>
        <pose>Unspecified</pose>
        <truncated>0</truncated>
        <occluded>0</occluded>
        <difficult>0</difficult>
        <bndbox>
            <xmin>47</xmin>
            <ymin>1106</ymin>
            <xmax>102</xmax>
            <ymax>1162</ymax>
        </bndbox>
    </object>
    <object>
        <name>Icon</name>
        <pose>Unspecified</pose>
        <truncated>0</truncated>
        <occluded>0</occluded>
        <difficult>0</difficult>
        <bndbox>
            <xmin>54</xmin>
            <ymin>981</ymin>
            <xmax>95</xmax>
            <ymax>1036</ymax>
        </bndbox>
    </object>
    <object>
        <name>Image</name>
        <pose>Unspecified</pose>
        <truncated>0</truncated>
        <occluded>0</occluded>
        <difficult>0</difficult>
        <bndbox>
            <xmin>49</xmin>
            <ymin>860</ymin>
            <xmax>99</xmax>
            <ymax>906</ymax>
        </bndbox>
    </object>
    <object>
        <name>Icon</name>
        <pose>Unspecified</pose>
        <truncated>0</truncated>
        <occluded>0</occluded>
        <difficult>0</difficult>
        <bndbox>
            <xmin>46</xmin>
            <ymin>728</ymin>
            <xmax>103</xmax>
            <ymax>785</ymax>
        </bndbox>
    </object>
    <object>
        <name>Icon</name>
        <pose>Unspecified</pose>
        <truncated>0</truncated>
        <occluded>0</occluded>
        <difficult>0</difficult>
        <bndbox>
            <xmin>47</xmin>
            <ymin>603</ymin>
            <xmax>102</xmax>
            <ymax>659</ymax>
        </bndbox>
    </object>
    <object>
        <name>Drawer</name>
        <pose>Unspecified</pose>
        <truncated>0</truncated>
        <occluded>0</occluded>
        <difficult>0</difficult>
        <bndbox>
            <xmin>1</xmin>
            <ymin>64</ymin>
            <xmax>736</xmax>
            <ymax>1794</ymax>
        </bndbox>
    </object>
    <object>
        <name>UpperTaskBar</name>
        <pose>Unspecified</pose>
        <truncated>0</truncated>
        <occluded>0</occluded>
        <difficult>0</difficult>
        <bndbox>
            <xmin>1</xmin>
            <ymin>1</ymin>
            <xmax>1080</xmax>
            <ymax>64</ymax>
        </bndbox>
    </object>
</annotation>
