<annotation>
    <folder>input_images_new</folder>
    <filename>71318.jpg</filename>
    <source>
        <database>Unknown</database>
    </source>
    <size>
        <width>1080</width>
        <height>1794</height>
        <depth>3</depth>
    </size>
    <segmented>0</segmented>
    <object>
        <name>Text</name>
        <pose>Unspecified</pose>
        <truncated>0</truncated>
        <occluded>0</occluded>
        <difficult>0</difficult>
        <bndbox>
            <xmin>322</xmin>
            <ymin>125</ymin>
            <xmax>759</xmax>
            <ymax>168</ymax>
        </bndbox>
    </object>
    <object>
        <name>Text</name>
        <pose>Unspecified</pose>
        <truncated>0</truncated>
        <occluded>0</occluded>
        <difficult>0</difficult>
        <bndbox>
            <xmin>166</xmin>
            <ymin>231</ymin>
            <xmax>914</xmax>
            <ymax>279</ymax>
        </bndbox>
    </object>
    <object>
        <name>Image</name>
        <pose>Unspecified</pose>
        <truncated>0</truncated>
        <occluded>0</occluded>
        <difficult>0</difficult>
        <bndbox>
            <xmin>318</xmin>
            <ymin>619</ymin>
            <xmax>764</xmax>
            <ymax>1409</ymax>
        </bndbox>
    </object>
    <object>
        <name>PageIndicator</name>
        <pose>Unspecified</pose>
        <truncated>0</truncated>
        <occluded>0</occluded>
        <difficult>0</difficult>
        <bndbox>
            <xmin>444</xmin>
            <ymin>1438</ymin>
            <xmax>627</xmax>
            <ymax>1463</ymax>
        </bndbox>
    </object>
    <object>
        <name>TextButton</name>
        <pose>Unspecified</pose>
        <truncated>0</truncated>
        <occluded>0</occluded>
        <difficult>0</difficult>
        <bndbox>
            <xmin>536</xmin>
            <ymin>1580</ymin>
            <xmax>943</xmax>
            <ymax>1708</ymax>
        </bndbox>
    </object>
    <object>
        <name>TextButton</name>
        <pose>Unspecified</pose>
        <truncated>0</truncated>
        <occluded>0</occluded>
        <difficult>0</difficult>
        <bndbox>
            <xmin>139</xmin>
            <ymin>1580</ymin>
            <xmax>516</xmax>
            <ymax>1708</ymax>
        </bndbox>
    </object>
</annotation>