<annotation>
    <folder>JPEGImages</folder>
    <filename>uplabs_81.jpg</filename>
    <size>
        <width>828</width>
        <height>1472</height>
        <depth>3</depth>
    </size>
    <object>
        <name>PageIndicator</name>
        <difficult>0</difficult>
        <bndbox>
            <xmin>36</xmin>
            <ymin>30</ymin>
            <xmax>134</xmax>
            <ymax>51</ymax>
        </bndbox>
    </object>
    <object>
        <name>Icon</name>
        <difficult>0</difficult>
        <bndbox>
            <xmin>713</xmin>
            <ymin>40</ymin>
            <xmax>797</xmax>
            <ymax>102</ymax>
        </bndbox>
    </object>
    <object>
        <name>Text</name>
        <difficult>0</difficult>
        <bndbox>
            <xmin>86</xmin>
            <ymin>322</ymin>
            <xmax>570</xmax>
            <ymax>372</ymax>
        </bndbox>
    </object>
    <object>
        <name>Text</name>
        <difficult>0</difficult>
        <bndbox>
            <xmin>351</xmin>
            <ymin>490</ymin>
            <xmax>465</xmax>
            <ymax>519</ymax>
        </bndbox>
    </object>
    <object>
        <name>Image</name>
        <difficult>0</difficult>
        <bndbox>
            <xmin>222</xmin>
            <ymin>612</ymin>
            <xmax>607</xmax>
            <ymax>1004</ymax>
        </bndbox>
    </object>
    <object>
        <name>Text</name>
        <difficult>0</difficult>
        <bndbox>
            <xmin>157</xmin>
            <ymin>1076</ymin>
            <xmax>627</xmax>
            <ymax>1111</ymax>
        </bndbox>
    </object>
    <object>
        <name>TextButton</name>
        <difficult>0</difficult>
        <bndbox>
            <xmin>183</xmin>
            <ymin>1262</ymin>
            <xmax>649</xmax>
            <ymax>1386</ymax>
        </bndbox>
    </object>
</annotation>