<annotation>
    <folder>input_images</folder>
    <filename>uplabs_340.jpg</filename>
    <source>
        <database>Unknown</database>
    </source>
    <size>
        <width>375</width>
        <height>812</height>
        <depth>3</depth>
    </size>
    <segmented>0</segmented>
    <object>
        <name>Text</name>
        <pose>Unspecified</pose>
        <truncated>0</truncated>
        <occluded>0</occluded>
        <difficult>0</difficult>
        <bndbox>
            <xmin>61</xmin>
            <ymin>73</ymin>
            <xmax>334</xmax>
            <ymax>101</ymax>
        </bndbox>
    </object>
    <object>
        <name>Text</name>
        <pose>Unspecified</pose>
        <truncated>0</truncated>
        <occluded>0</occluded>
        <difficult>0</difficult>
        <bndbox>
            <xmin>81</xmin>
            <ymin>117</ymin>
            <xmax>312</xmax>
            <ymax>133</ymax>
        </bndbox>
    </object>
    <object>
        <name>Text</name>
        <pose>Unspecified</pose>
        <truncated>0</truncated>
        <occluded>0</occluded>
        <difficult>0</difficult>
        <bndbox>
            <xmin>40</xmin>
            <ymin>575</ymin>
            <xmax>332</xmax>
            <ymax>637</ymax>
        </bndbox>
    </object>
    <object>
        <name>PageIndicator</name>
        <pose>Unspecified</pose>
        <truncated>0</truncated>
        <occluded>0</occluded>
        <difficult>0</difficult>
        <bndbox>
            <xmin>141</xmin>
            <ymin>671</ymin>
            <xmax>235</xmax>
            <ymax>701</ymax>
        </bndbox>
    </object>
    <object>
        <name>Image</name>
        <pose>Unspecified</pose>
        <truncated>0</truncated>
        <occluded>0</occluded>
        <difficult>0</difficult>
        <bndbox>
            <xmin>40</xmin>
            <ymin>237</ymin>
            <xmax>337</xmax>
            <ymax>467</ymax>
        </bndbox>
    </object>
</annotation>