<annotation>
    <folder>JPEGImages</folder>
    <filename>uplabs_418.jpg</filename>
    <size>
        <width>1162</width>
        <height>2027</height>
        <depth>3</depth>
    </size>
    <object>
        <name>Image</name>
        <difficult>0</difficult>
        <bndbox>
            <xmin>346</xmin>
            <ymin>1165</ymin>
            <xmax>788</xmax>
            <ymax>1308</ymax>
        </bndbox>
    </object>
    <object>
        <name>Text</name>
        <difficult>0</difficult>
        <bndbox>
            <xmin>341</xmin>
            <ymin>1369</ymin>
            <xmax>824</xmax>
            <ymax>1507</ymax>
        </bndbox>
    </object>
    <object>
        <name>PageIndicator</name>
        <difficult>0</difficult>
        <bndbox>
            <xmin>503</xmin>
            <ymin>1671</ymin>
            <xmax>663</xmax>
            <ymax>1699</ymax>
        </bndbox>
    </object>
    <object>
        <name>Text</name>
        <difficult>0</difficult>
        <bndbox>
            <xmin>899</xmin>
            <ymin>1854</ymin>
            <xmax>1026</xmax>
            <ymax>1903</ymax>
        </bndbox>
    </object>
    <object>
        <name>Text</name>
        <difficult>0</difficult>
        <bndbox>
            <xmin>139</xmin>
            <ymin>1852</ymin>
            <xmax>248</xmax>
            <ymax>1915</ymax>
        </bndbox>
    </object>
    <object>
        <name>BackgroundImage</name>
        <difficult>0</difficult>
        <bndbox>
            <xmin>42</xmin>
            <ymin>42</ymin>
            <xmax>1122</xmax>
            <ymax>1987</ymax>
        </bndbox>
    </object>
</annotation>
